macos/__init__.py
macos.flashon_api-0.5.4.dist-info/METADATA
macos.flashon_api-0.5.4.dist-info/WHEEL
macos.flashon_api-0.5.4.dist-info/top_level.txt
macos.flashon_api-0.5.4.dist-info/RECORD
